open_fda_drug_label/.DS_Store
open_fda_drug_label/__init__.py
open_fda_drug_label/api.py
open_fda_drug_label/drug.py
open_fda_drug_label/open_fda_drug_label.py
open_fda_drug_label/shelf.py
open_fda_drug_label-0.1.0.dist-info/METADATA
open_fda_drug_label-0.1.0.dist-info/WHEEL
open_fda_drug_label-0.1.0.dist-info/licenses/LICENSE
open_fda_drug_label-0.1.0.dist-info/RECORD
