Metadata-Version: 2.4
Name: open_fda_drug_label
Version: 0.1.0
Summary: Package leveraging openFDA drug/label API to access drug information and store in usable python data objects
License: MIT
License-File: LICENSE
Author: Leo Jergovic
Requires-Python: >=3.12,<4.0
Classifier: License :: OSI Approved :: MIT License
Classifier: Programming Language :: Python :: 3
Classifier: Programming Language :: Python :: 3.12
Classifier: Programming Language :: Python :: 3.13
Classifier: Programming Language :: Python :: 3.14
Requires-Dist: dotenv (>=0.9.9,<0.10.0)
Requires-Dist: requests (>=2.32.5,<3.0.0)
Project-URL: Documentation, https://open-fda-drug-label.readthedocs.io/en/latest/#
Project-URL: Homepage, https://github.com/thefleok/open_fda_drug_label
Project-URL: Repository, https://github.com/thefleok/open_fda_drug_label
